lueur-0.22.5.dist-info/METADATA
lueur-0.22.5.dist-info/WHEEL
lueur-0.22.5.dist-info/entry_points.txt
lueur-0.22.5.dist-info/licenses/LICENSE
lueur/__init__.py
lueur/api/__init__.py
lueur/api/gcp/__init__.py
lueur/api/gcp/lb.py
lueur/date_time.py
lueur/disco.py
lueur/links.py
lueur/make_id.py
lueur/models.py
lueur/platform/__init__.py
lueur/platform/aws/__init__.py
lueur/platform/aws/client.py
lueur/platform/aws/ec2.py
lueur/platform/aws/ecr.py
lueur/platform/aws/eks.py
lueur/platform/aws/lb.py
lueur/platform/aws/region.py
lueur/platform/aws/vpc.py
lueur/platform/gcp/__init__.py
lueur/platform/gcp/address.py
lueur/platform/gcp/client.py
lueur/platform/gcp/cloudrun.py
lueur/platform/gcp/compute.py
lueur/platform/gcp/connector.py
lueur/platform/gcp/dns.py
lueur/platform/gcp/firewall.py
lueur/platform/gcp/forwardingrule.py
lueur/platform/gcp/gke.py
lueur/platform/gcp/healthchecks.py
lueur/platform/gcp/lb.py
lueur/platform/gcp/memorystore.py
lueur/platform/gcp/monitoring.py
lueur/platform/gcp/project.py
lueur/platform/gcp/region.py
lueur/platform/gcp/securities.py
lueur/platform/gcp/sql.py
lueur/platform/gcp/storage.py
lueur/platform/gcp/targetproxy.py
lueur/platform/gcp/vpc.py
lueur/platform/gcp/zone.py
lueur/platform/grafana/__init__.py
lueur/platform/grafana/alert.py
lueur/platform/grafana/client.py
lueur/platform/grafana/incident.py
lueur/platform/grafana/slo.py
lueur/platform/grafana/team.py
lueur/platform/k8s/__init__.py
lueur/platform/k8s/client.py
lueur/platform/k8s/dependency.py
lueur/platform/k8s/deployment.py
lueur/platform/k8s/gateway.py
lueur/platform/k8s/ingress.py
lueur/platform/k8s/network_policy.py
lueur/platform/k8s/node.py
lueur/platform/k8s/pod.py
lueur/platform/k8s/replicaset.py
lueur/platform/k8s/service.py
lueur/resource.py
lueur/rules.py
lueur/serializer.py
lueur/text.py
lueur-0.22.5.dist-info/RECORD
