Metadata-Version: 2.1
Name: lueur
Version: 0.22.5
Summary: Lueur library
Author-Email: Sylvain Hellegouarch <sh@defuze.org>
License: Apache-2.0
Classifier: Development Status :: 5 - Production/Stable
Classifier: Intended Audience :: Developers
Classifier: License :: OSI Approved :: Apache Software License
Classifier: Programming Language :: Python
Classifier: Programming Language :: Python :: 3.11
Classifier: Programming Language :: Python :: 3.12
Classifier: Programming Language :: Python :: 3.13
Classifier: Programming Language :: Python :: Implementation :: CPython
Project-URL: Documentation, https://lueur.dev/
Project-URL: Issues, https://github.com/lueurdev/lueur-python-lib/issues
Project-URL: Source, https://github.com/lueurdev/lueur-python-lib
Requires-Python: <4,>=3.11
Requires-Dist: httpx[http2]>=0.27.0
Requires-Dist: pydantic>=2.7.4
Requires-Dist: msgspec>=0.18.6
Requires-Dist: python-jsonpath>=1.1.1
Provides-Extra: gcp
Requires-Dist: google-auth>=2.30.0; extra == "gcp"
Requires-Dist: tenacity>=9.0.0; extra == "gcp"
Provides-Extra: k8s
Requires-Dist: kubernetes>=30.1.0; extra == "k8s"
Provides-Extra: aws
Requires-Dist: boto3>=1.34.131; extra == "aws"
